dataproperty/__init__.py
dataproperty/__version__.py
dataproperty/_align.py
dataproperty/_align_getter.py
dataproperty/_base.py
dataproperty/_column.py
dataproperty/_common.py
dataproperty/_container.py
dataproperty/_converter.py
dataproperty/_dataproperty.py
dataproperty/_extractor.py
dataproperty/_formatter.py
dataproperty/_function.py
dataproperty/_interface.py
dataproperty/_line_break.py
dataproperty/_preprocessor.py
dataproperty/py.typed
dataproperty/typing.py
dataproperty/logger/__init__.py
dataproperty/logger/_logger.py
dataproperty/logger/_null_logger.py
DataProperty-1.0.2.dist-info/LICENSE
DataProperty-1.0.2.dist-info/METADATA
DataProperty-1.0.2.dist-info/WHEEL
DataProperty-1.0.2.dist-info/top_level.txt
DataProperty-1.0.2.dist-info/RECORD
