Metadata-Version: 2.1
Name: DataProperty
Version: 1.0.2
Summary: Python library for extract property from data.
Home-page: https://github.com/thombashi/DataProperty
Author: Tsuyoshi Hombashi
Author-email: tsuyoshi.hombashi@gmail.com
Maintainer: Tsuyoshi Hombashi
Maintainer-email: tsuyoshi.hombashi@gmail.com
License: MIT License
Project-URL: Changelog, https://github.com/thombashi/DataProperty/releases
Project-URL: Source, https://github.com/thombashi/DataProperty
Project-URL: Tracker, https://github.com/thombashi/DataProperty/issues
Keywords: data,library,property
Classifier: Development Status :: 5 - Production/Stable
Classifier: Intended Audience :: Developers
Classifier: Intended Audience :: Information Technology
Classifier: License :: OSI Approved :: MIT License
Classifier: Operating System :: OS Independent
Classifier: Programming Language :: Python :: 3
Classifier: Programming Language :: Python :: 3.9
Classifier: Programming Language :: Python :: 3.10
Classifier: Programming Language :: Python :: 3.11
Classifier: Programming Language :: Python :: 3.12
Classifier: Programming Language :: Python :: 3.13
Classifier: Programming Language :: Python :: Implementation :: CPython
Classifier: Programming Language :: Python :: Implementation :: PyPy
Classifier: Topic :: Software Development :: Libraries
Classifier: Topic :: Software Development :: Libraries :: Python Modules
Classifier: Typing :: Typed
Requires-Python: >=3.9
License-File: LICENSE
Requires-Dist: mbstrdecoder<2,>=1.0.0
Requires-Dist: typepy[datetime]<2,>=1.3.2
Provides-Extra: logging
Requires-Dist: loguru<1,>=0.4.1; extra == "logging"
Provides-Extra: test
Requires-Dist: pytest>=6.0.1; extra == "test"
Requires-Dist: pytest-md-report>=0.6.2; extra == "test"
Requires-Dist: tcolorpy>=0.1.2; extra == "test"
